meipai/__init__.py
meipai/api.py
meipai/cache.py
meipai/player.py
meipai-0.1.2.dist-info/DESCRIPTION.rst
meipai-0.1.2.dist-info/METADATA
meipai-0.1.2.dist-info/RECORD
meipai-0.1.2.dist-info/WHEEL
meipai-0.1.2.dist-info/entry_points.txt
meipai-0.1.2.dist-info/metadata.json
meipai-0.1.2.dist-info/top_level.txt
