Metadata-Version: 2.0
Name: meipai
Version: 0.1.2
Summary: A command line interface to search,play videos on meipai
Home-page: https://github.com/PyBeaner/meipai
Author: PyBeaner
Author-email: 758046738@qq.com
License: MIT
Keywords: meipai,video,cli
Platform: UNKNOWN
Requires-Dist: BeautifulSoup4
Requires-Dist: requests
